{
  "prompt_00000": {
    "status": "done",
    "completed_at": "2026-05-11T23:38:30.696995+00:00",
    "duration": 2.24
  },
  "prompt_00001": {
    "status": "done",
    "completed_at": "2026-05-11T23:38:42.940516+00:00",
    "duration": 3.2
  },
  "prompt_00002": {
    "status": "done",
    "completed_at": "2026-05-11T23:38:56.289827+00:00",
    "duration": 3.72
  },
  "prompt_00003": {
    "status": "done",
    "completed_at": "2026-05-11T23:39:06.643929+00:00",
    "duration": 2.44
  },
  "prompt_00004": {
    "status": "done",
    "completed_at": "2026-05-11T23:39:19.370132+00:00",
    "duration": 3.4
  },
  "prompt_00005": {
    "status": "done",
    "completed_at": "2026-05-11T23:39:32.483286+00:00",
    "duration": 3.44
  },
  "prompt_00006": {
    "status": "done",
    "completed_at": "2026-05-11T23:39:41.425540+00:00",
    "duration": 1.92
  },
  "prompt_00007": {
    "status": "done",
    "completed_at": "2026-05-11T23:39:52.458057+00:00",
    "duration": 2.6
  },
  "prompt_00008": {
    "status": "done",
    "completed_at": "2026-05-11T23:40:03.131373+00:00",
    "duration": 2.44
  },
  "prompt_00009": {
    "status": "done",
    "completed_at": "2026-05-11T23:40:12.825304+00:00",
    "duration": 2.08
  },
  "prompt_00010": {
    "status": "done",
    "completed_at": "2026-05-11T23:40:29.100205+00:00",
    "duration": 3.72
  },
  "prompt_00011": {
    "status": "done",
    "completed_at": "2026-05-11T23:40:44.061874+00:00",
    "duration": 2.64
  },
  "prompt_00012": {
    "status": "done",
    "completed_at": "2026-05-11T23:41:01.916715+00:00",
    "duration": 3.48
  },
  "prompt_00013": {
    "status": "done",
    "completed_at": "2026-05-11T23:41:20.336855+00:00",
    "duration": 3.76
  },
  "prompt_00014": {
    "status": "done",
    "completed_at": "2026-05-11T23:41:34.879554+00:00",
    "duration": 2.68
  },
  "prompt_00015": {
    "status": "done",
    "completed_at": "2026-05-11T23:41:46.961035+00:00",
    "duration": 1.92
  },
  "prompt_00016": {
    "status": "done",
    "completed_at": "2026-05-11T23:42:03.327629+00:00",
    "duration": 3.4
  },
  "prompt_00017": {
    "status": "done",
    "completed_at": "2026-05-11T23:42:17.468379+00:00",
    "duration": 2.6
  },
  "prompt_00018": {
    "status": "done",
    "completed_at": "2026-05-11T23:42:31.633471+00:00",
    "duration": 2.6
  },
  "prompt_00019": {
    "status": "done",
    "completed_at": "2026-05-11T23:42:48.099434+00:00",
    "duration": 3.24
  },
  "prompt_00020": {
    "status": "done",
    "completed_at": "2026-05-11T23:43:03.416027+00:00",
    "duration": 2.88
  },
  "prompt_00021": {
    "status": "done",
    "completed_at": "2026-05-11T23:43:22.157664+00:00",
    "duration": 3.72
  },
  "prompt_00022": {
    "status": "done",
    "completed_at": "2026-05-11T23:43:36.279502+00:00",
    "duration": 2.36
  },
  "prompt_00023": {
    "status": "done",
    "completed_at": "2026-05-11T23:43:51.468710+00:00",
    "duration": 2.92
  },
  "prompt_00024": {
    "status": "done",
    "completed_at": "2026-05-11T23:44:05.258902+00:00",
    "duration": 2.6
  },
  "prompt_00025": {
    "status": "done",
    "completed_at": "2026-05-11T23:44:20.975631+00:00",
    "duration": 3.24
  },
  "prompt_00026": {
    "status": "done",
    "completed_at": "2026-05-11T23:44:36.769098+00:00",
    "duration": 3.2
  },
  "prompt_00027": {
    "status": "done",
    "completed_at": "2026-05-11T23:44:53.275360+00:00",
    "duration": 3.48
  },
  "prompt_00028": {
    "status": "done",
    "completed_at": "2026-05-11T23:45:08.367851+00:00",
    "duration": 3.04
  },
  "prompt_00029": {
    "status": "done",
    "completed_at": "2026-05-11T23:45:24.939712+00:00",
    "duration": 3.6
  },
  "prompt_00030": {
    "status": "done",
    "completed_at": "2026-05-11T23:45:42.961988+00:00",
    "duration": 4.04
  },
  "prompt_00031": {
    "status": "done",
    "completed_at": "2026-05-11T23:45:56.609262+00:00",
    "duration": 2.64
  },
  "prompt_00032": {
    "status": "done",
    "completed_at": "2026-05-11T23:46:15.036205+00:00",
    "duration": 4.0
  },
  "prompt_00033": {
    "status": "done",
    "completed_at": "2026-05-11T23:46:28.620703+00:00",
    "duration": 2.6
  },
  "prompt_00034": {
    "status": "done",
    "completed_at": "2026-05-11T23:46:42.064979+00:00",
    "duration": 2.56
  },
  "prompt_00035": {
    "status": "done",
    "completed_at": "2026-05-11T23:46:54.153586+00:00",
    "duration": 2.12
  },
  "prompt_00036": {
    "status": "done",
    "completed_at": "2026-05-11T23:47:09.269516+00:00",
    "duration": 3.12
  },
  "prompt_00037": {
    "status": "done",
    "completed_at": "2026-05-11T23:47:24.444565+00:00",
    "duration": 3.12
  },
  "prompt_00038": {
    "status": "done",
    "completed_at": "2026-05-11T23:47:39.930514+00:00",
    "duration": 3.24
  },
  "prompt_00039": {
    "status": "done",
    "completed_at": "2026-05-11T23:47:53.753109+00:00",
    "duration": 2.68
  },
  "prompt_00040": {
    "status": "done",
    "completed_at": "2026-05-11T23:48:08.792760+00:00",
    "duration": 3.08
  },
  "prompt_00041": {
    "status": "done",
    "completed_at": "2026-05-11T23:48:24.307933+00:00",
    "duration": 3.24
  },
  "prompt_00042": {
    "status": "done",
    "completed_at": "2026-05-11T23:48:38.142880+00:00",
    "duration": 2.68
  },
  "prompt_00043": {
    "status": "done",
    "completed_at": "2026-05-11T23:48:53.014253+00:00",
    "duration": 2.92
  },
  "prompt_00044": {
    "status": "done",
    "completed_at": "2026-05-11T23:49:08.693879+00:00",
    "duration": 3.28
  },
  "prompt_00045": {
    "status": "done",
    "completed_at": "2026-05-11T23:49:24.159319+00:00",
    "duration": 3.24
  },
  "prompt_00046": {
    "status": "done",
    "completed_at": "2026-05-11T23:49:40.521015+00:00",
    "duration": 3.52
  },
  "prompt_00047": {
    "status": "done",
    "completed_at": "2026-05-11T23:49:54.927079+00:00",
    "duration": 2.8
  },
  "prompt_00048": {
    "status": "done",
    "completed_at": "2026-05-11T23:50:11.203419+00:00",
    "duration": 3.48
  },
  "prompt_00049": {
    "status": "done",
    "completed_at": "2026-05-11T23:50:24.494153+00:00",
    "duration": 2.48
  },
  "prompt_00050": {
    "status": "done",
    "completed_at": "2026-05-11T23:50:40.775468+00:00",
    "duration": 3.52
  },
  "prompt_00051": {
    "status": "done",
    "completed_at": "2026-05-11T23:50:54.666009+00:00",
    "duration": 2.56
  },
  "prompt_00052": {
    "status": "done",
    "completed_at": "2026-05-11T23:51:10.502211+00:00",
    "duration": 3.12
  },
  "prompt_00053": {
    "status": "done",
    "completed_at": "2026-05-11T23:51:29.448921+00:00",
    "duration": 3.96
  },
  "prompt_00054": {
    "status": "done",
    "completed_at": "2026-05-11T23:51:44.099565+00:00",
    "duration": 2.72
  },
  "prompt_00055": {
    "status": "done",
    "completed_at": "2026-05-11T23:52:00.388180+00:00",
    "duration": 3.44
  },
  "prompt_00056": {
    "status": "done",
    "completed_at": "2026-05-11T23:52:16.565711+00:00",
    "duration": 3.44
  },
  "prompt_00057": {
    "status": "done",
    "completed_at": "2026-05-11T23:52:33.564991+00:00",
    "duration": 3.64
  },
  "prompt_00058": {
    "status": "done",
    "completed_at": "2026-05-11T23:52:47.771891+00:00",
    "duration": 2.8
  },
  "prompt_00059": {
    "status": "done",
    "completed_at": "2026-05-11T23:53:03.621109+00:00",
    "duration": 3.32
  },
  "prompt_00060": {
    "status": "done",
    "completed_at": "2026-05-11T23:53:19.964197+00:00",
    "duration": 3.36
  },
  "prompt_00061": {
    "status": "done",
    "completed_at": "2026-05-11T23:53:35.707923+00:00",
    "duration": 3.32
  },
  "prompt_00062": {
    "status": "done",
    "completed_at": "2026-05-11T23:53:50.925133+00:00",
    "duration": 3.12
  },
  "prompt_00063": {
    "status": "done",
    "completed_at": "2026-05-11T23:54:07.198246+00:00",
    "duration": 3.48
  },
  "prompt_00064": {
    "status": "done",
    "completed_at": "2026-05-11T23:54:20.794533+00:00",
    "duration": 2.6
  },
  "prompt_00065": {
    "status": "done",
    "completed_at": "2026-05-11T23:54:34.663196+00:00",
    "duration": 2.72
  },
  "prompt_00066": {
    "status": "done",
    "completed_at": "2026-05-11T23:54:48.986990+00:00",
    "duration": 2.88
  },
  "prompt_00067": {
    "status": "done",
    "completed_at": "2026-05-11T23:55:02.981147+00:00",
    "duration": 2.72
  },
  "prompt_00068": {
    "status": "done",
    "completed_at": "2026-05-11T23:55:17.385145+00:00",
    "duration": 2.8
  },
  "prompt_00069": {
    "status": "done",
    "completed_at": "2026-05-11T23:55:33.924203+00:00",
    "duration": 3.52
  },
  "prompt_00070": {
    "status": "done",
    "completed_at": "2026-05-11T23:55:52.028419+00:00",
    "duration": 3.84
  },
  "prompt_00071": {
    "status": "done",
    "completed_at": "2026-05-11T23:56:11.074755+00:00",
    "duration": 4.0
  },
  "prompt_00072": {
    "status": "done",
    "completed_at": "2026-05-11T23:56:27.086994+00:00",
    "duration": 3.08
  },
  "prompt_00073": {
    "status": "done",
    "completed_at": "2026-05-11T23:56:40.494225+00:00",
    "duration": 2.24
  },
  "prompt_00074": {
    "status": "done",
    "completed_at": "2026-05-11T23:56:55.524711+00:00",
    "duration": 2.76
  },
  "prompt_00075": {
    "status": "done",
    "completed_at": "2026-05-11T23:57:10.259960+00:00",
    "duration": 2.68
  },
  "prompt_00076": {
    "status": "done",
    "completed_at": "2026-05-11T23:57:23.298222+00:00",
    "duration": 2.16
  },
  "prompt_00077": {
    "status": "done",
    "completed_at": "2026-05-11T23:57:39.608414+00:00",
    "duration": 3.16
  },
  "prompt_00078": {
    "status": "done",
    "completed_at": "2026-05-11T23:57:57.465517+00:00",
    "duration": 3.64
  },
  "prompt_00079": {
    "status": "done",
    "completed_at": "2026-05-11T23:58:10.714643+00:00",
    "duration": 2.24
  },
  "prompt_00080": {
    "status": "done",
    "completed_at": "2026-05-11T23:58:24.269924+00:00",
    "duration": 2.28
  },
  "prompt_00081": {
    "status": "done",
    "completed_at": "2026-05-11T23:58:40.415807+00:00",
    "duration": 3.12
  },
  "prompt_00082": {
    "status": "done",
    "completed_at": "2026-05-11T23:58:53.826096+00:00",
    "duration": 2.32
  },
  "prompt_00083": {
    "status": "done",
    "completed_at": "2026-05-11T23:59:07.351595+00:00",
    "duration": 2.6
  },
  "prompt_00084": {
    "status": "done",
    "completed_at": "2026-05-11T23:59:20.142942+00:00",
    "duration": 2.36
  },
  "prompt_00085": {
    "status": "done",
    "completed_at": "2026-05-11T23:59:35.306631+00:00",
    "duration": 3.12
  },
  "prompt_00086": {
    "status": "done",
    "completed_at": "2026-05-11T23:59:51.471707+00:00",
    "duration": 3.44
  },
  "prompt_00087": {
    "status": "done",
    "completed_at": "2026-05-12T00:00:06.515309+00:00",
    "duration": 3.08
  },
  "prompt_00088": {
    "status": "done",
    "completed_at": "2026-05-12T00:00:21.920230+00:00",
    "duration": 3.2
  },
  "prompt_00089": {
    "status": "done",
    "completed_at": "2026-05-12T00:00:36.022186+00:00",
    "duration": 2.8
  },
  "prompt_00090": {
    "status": "done",
    "completed_at": "2026-05-12T00:00:47.768926+00:00",
    "duration": 2.04
  },
  "prompt_00091": {
    "status": "done",
    "completed_at": "2026-05-12T00:01:00.071914+00:00",
    "duration": 2.2
  },
  "prompt_00092": {
    "status": "done",
    "completed_at": "2026-05-12T00:01:13.592626+00:00",
    "duration": 2.6
  },
  "prompt_00093": {
    "status": "done",
    "completed_at": "2026-05-12T00:01:25.769613+00:00",
    "duration": 2.16
  },
  "prompt_00094": {
    "status": "done",
    "completed_at": "2026-05-12T00:01:36.259029+00:00",
    "duration": 1.6
  },
  "prompt_00095": {
    "status": "done",
    "completed_at": "2026-05-12T00:01:47.573389+00:00",
    "duration": 1.92
  },
  "prompt_00096": {
    "status": "done",
    "completed_at": "2026-05-12T00:02:00.475106+00:00",
    "duration": 2.4
  },
  "prompt_00097": {
    "status": "done",
    "completed_at": "2026-05-12T00:02:12.726830+00:00",
    "duration": 2.24
  },
  "prompt_00098": {
    "status": "done",
    "completed_at": "2026-05-12T00:02:27.296380+00:00",
    "duration": 2.96
  },
  "prompt_00099": {
    "status": "done",
    "completed_at": "2026-05-12T00:02:40.681983+00:00",
    "duration": 2.32
  },
  "prompt_00100": {
    "status": "done",
    "completed_at": "2026-05-12T00:02:56.121852+00:00",
    "duration": 2.92
  },
  "prompt_00101": {
    "status": "done",
    "completed_at": "2026-05-12T00:03:11.387752+00:00",
    "duration": 3.04
  },
  "prompt_00102": {
    "status": "done",
    "completed_at": "2026-05-12T00:03:28.743383+00:00",
    "duration": 3.56
  },
  "prompt_00103": {
    "status": "done",
    "completed_at": "2026-05-12T00:03:43.632407+00:00",
    "duration": 2.76
  },
  "prompt_00104": {
    "status": "done",
    "completed_at": "2026-05-12T00:04:00.666109+00:00",
    "duration": 3.44
  },
  "prompt_00105": {
    "status": "done",
    "completed_at": "2026-05-12T00:04:14.552932+00:00",
    "duration": 2.4
  },
  "prompt_00106": {
    "status": "done",
    "completed_at": "2026-05-12T00:04:30.336165+00:00",
    "duration": 2.96
  },
  "prompt_00107": {
    "status": "done",
    "completed_at": "2026-05-12T00:04:45.868230+00:00",
    "duration": 3.08
  },
  "prompt_00108": {
    "status": "done",
    "completed_at": "2026-05-12T00:05:02.646794+00:00",
    "duration": 3.6
  },
  "prompt_00109": {
    "status": "done",
    "completed_at": "2026-05-12T00:05:18.186321+00:00",
    "duration": 3.2
  },
  "prompt_00110": {
    "status": "done",
    "completed_at": "2026-05-12T00:05:30.857549+00:00",
    "duration": 2.32
  },
  "prompt_00111": {
    "status": "done",
    "completed_at": "2026-05-12T00:05:43.700171+00:00",
    "duration": 2.4
  },
  "prompt_00112": {
    "status": "done",
    "completed_at": "2026-05-12T00:05:56.483175+00:00",
    "duration": 2.36
  },
  "prompt_00113": {
    "status": "done",
    "completed_at": "2026-05-12T00:06:08.923155+00:00",
    "duration": 2.24
  },
  "prompt_00114": {
    "status": "done",
    "completed_at": "2026-05-12T00:06:20.658281+00:00",
    "duration": 2.04
  },
  "prompt_00115": {
    "status": "done",
    "completed_at": "2026-05-12T00:06:34.103222+00:00",
    "duration": 2.6
  },
  "prompt_00116": {
    "status": "done",
    "completed_at": "2026-05-12T00:06:48.102038+00:00",
    "duration": 2.72
  },
  "prompt_00117": {
    "status": "done",
    "completed_at": "2026-05-12T00:07:04.255323+00:00",
    "duration": 3.4
  },
  "prompt_00118": {
    "status": "done",
    "completed_at": "2026-05-12T00:07:16.668368+00:00",
    "duration": 2.2
  },
  "prompt_00119": {
    "status": "done",
    "completed_at": "2026-05-12T00:07:31.032788+00:00",
    "duration": 2.84
  },
  "prompt_00120": {
    "status": "done",
    "completed_at": "2026-05-12T00:07:47.507478+00:00",
    "duration": 3.32
  },
  "prompt_00121": {
    "status": "done",
    "completed_at": "2026-05-12T00:08:00.234415+00:00",
    "duration": 2.08
  },
  "prompt_00122": {
    "status": "done",
    "completed_at": "2026-05-12T00:08:11.925958+00:00",
    "duration": 1.88
  },
  "prompt_00123": {
    "status": "done",
    "completed_at": "2026-05-12T00:08:25.558670+00:00",
    "duration": 2.48
  },
  "prompt_00124": {
    "status": "done",
    "completed_at": "2026-05-12T00:08:39.662275+00:00",
    "duration": 2.6
  },
  "prompt_00125": {
    "status": "done",
    "completed_at": "2026-05-12T00:08:54.003133+00:00",
    "duration": 2.68
  },
  "prompt_00126": {
    "status": "done",
    "completed_at": "2026-05-12T00:09:07.323486+00:00",
    "duration": 2.24
  },
  "prompt_00127": {
    "status": "done",
    "completed_at": "2026-05-12T00:09:22.873496+00:00",
    "duration": 2.8
  },
  "prompt_00128": {
    "status": "done",
    "completed_at": "2026-05-12T00:09:36.883219+00:00",
    "duration": 2.76
  },
  "prompt_00129": {
    "status": "done",
    "completed_at": "2026-05-12T00:09:51.183423+00:00",
    "duration": 2.84
  },
  "prompt_00130": {
    "status": "done",
    "completed_at": "2026-05-12T00:10:02.923151+00:00",
    "duration": 2.04
  },
  "prompt_00131": {
    "status": "done",
    "completed_at": "2026-05-12T00:10:13.176133+00:00",
    "duration": 1.52
  },
  "prompt_00132": {
    "status": "done",
    "completed_at": "2026-05-12T00:10:24.923867+00:00",
    "duration": 2.0
  },
  "prompt_00133": {
    "status": "done",
    "completed_at": "2026-05-12T00:10:39.984805+00:00",
    "duration": 3.12
  },
  "prompt_00134": {
    "status": "done",
    "completed_at": "2026-05-12T00:10:50.383093+00:00",
    "duration": 1.6
  },
  "prompt_00135": {
    "status": "done",
    "completed_at": "2026-05-12T00:11:01.444262+00:00",
    "duration": 1.8
  },
  "prompt_00136": {
    "status": "done",
    "completed_at": "2026-05-12T00:11:11.481885+00:00",
    "duration": 1.44
  },
  "prompt_00137": {
    "status": "done",
    "completed_at": "2026-05-12T00:11:23.154448+00:00",
    "duration": 1.72
  },
  "prompt_00138": {
    "status": "done",
    "completed_at": "2026-05-12T00:11:34.587503+00:00",
    "duration": 1.72
  },
  "prompt_00139": {
    "status": "done",
    "completed_at": "2026-05-12T00:11:44.705095+00:00",
    "duration": 1.44
  },
  "prompt_00140": {
    "status": "done",
    "completed_at": "2026-05-12T00:11:56.631715+00:00",
    "duration": 2.0
  },
  "prompt_00141": {
    "status": "done",
    "completed_at": "2026-05-12T00:12:08.644726+00:00",
    "duration": 1.76
  },
  "prompt_00142": {
    "status": "done",
    "completed_at": "2026-05-12T00:12:20.496813+00:00",
    "duration": 1.96
  },
  "prompt_00143": {
    "status": "done",
    "completed_at": "2026-05-12T00:12:31.190985+00:00",
    "duration": 1.64
  },
  "prompt_00144": {
    "status": "done",
    "completed_at": "2026-05-12T00:12:41.276673+00:00",
    "duration": 1.52
  },
  "prompt_00145": {
    "status": "done",
    "completed_at": "2026-05-12T00:12:51.455592+00:00",
    "duration": 1.52
  },
  "prompt_00146": {
    "status": "done",
    "completed_at": "2026-05-12T00:13:05.070059+00:00",
    "duration": 2.64
  },
  "prompt_00147": {
    "status": "done",
    "completed_at": "2026-05-12T00:13:14.598640+00:00",
    "duration": 1.32
  },
  "prompt_00148": {
    "status": "done",
    "completed_at": "2026-05-12T00:13:24.140812+00:00",
    "duration": 1.28
  },
  "prompt_00149": {
    "status": "done",
    "completed_at": "2026-05-12T00:13:34.394305+00:00",
    "duration": 1.52
  },
  "prompt_00150": {
    "status": "done",
    "completed_at": "2026-05-12T00:13:44.401051+00:00",
    "duration": 1.44
  },
  "prompt_00151": {
    "status": "done",
    "completed_at": "2026-05-12T00:13:56.697601+00:00",
    "duration": 2.16
  },
  "prompt_00152": {
    "status": "done",
    "completed_at": "2026-05-12T00:14:08.455603+00:00",
    "duration": 2.04
  },
  "prompt_00153": {
    "status": "done",
    "completed_at": "2026-05-12T00:14:17.907202+00:00",
    "duration": 1.28
  },
  "prompt_00154": {
    "status": "done",
    "completed_at": "2026-05-12T00:14:29.532676+00:00",
    "duration": 1.92
  },
  "prompt_00155": {
    "status": "done",
    "completed_at": "2026-05-12T00:14:38.191422+00:00",
    "duration": 1.0
  },
  "prompt_00156": {
    "status": "done",
    "completed_at": "2026-05-12T00:14:49.238214+00:00",
    "duration": 1.76
  },
  "prompt_00157": {
    "status": "done",
    "completed_at": "2026-05-12T00:15:01.830575+00:00",
    "duration": 2.2
  },
  "prompt_00158": {
    "status": "done",
    "completed_at": "2026-05-12T00:15:11.819264+00:00",
    "duration": 1.36
  },
  "prompt_00159": {
    "status": "done",
    "completed_at": "2026-05-12T00:15:21.422510+00:00",
    "duration": 1.32
  },
  "prompt_00160": {
    "status": "done",
    "completed_at": "2026-05-12T00:15:32.682263+00:00",
    "duration": 1.8
  },
  "prompt_00161": {
    "status": "done",
    "completed_at": "2026-05-12T00:15:44.568784+00:00",
    "duration": 2.0
  },
  "prompt_00162": {
    "status": "done",
    "completed_at": "2026-05-12T00:15:58.145543+00:00",
    "duration": 2.56
  },
  "prompt_00163": {
    "status": "done",
    "completed_at": "2026-05-12T00:16:09.926786+00:00",
    "duration": 2.0
  },
  "prompt_00164": {
    "status": "done",
    "completed_at": "2026-05-12T00:16:19.196935+00:00",
    "duration": 1.16
  },
  "prompt_00165": {
    "status": "done",
    "completed_at": "2026-05-12T00:16:28.775645+00:00",
    "duration": 1.28
  },
  "prompt_00166": {
    "status": "done",
    "completed_at": "2026-05-12T00:16:40.064383+00:00",
    "duration": 1.76
  },
  "prompt_00167": {
    "status": "done",
    "completed_at": "2026-05-12T00:16:50.615903+00:00",
    "duration": 1.6
  },
  "prompt_00168": {
    "status": "done",
    "completed_at": "2026-05-12T00:17:00.478632+00:00",
    "duration": 1.36
  },
  "prompt_00169": {
    "status": "done",
    "completed_at": "2026-05-12T00:17:10.451823+00:00",
    "duration": 1.4
  },
  "prompt_00170": {
    "status": "done",
    "completed_at": "2026-05-12T00:17:22.385971+00:00",
    "duration": 2.04
  },
  "prompt_00171": {
    "status": "done",
    "completed_at": "2026-05-12T00:17:36.284545+00:00",
    "duration": 2.64
  },
  "prompt_00172": {
    "status": "done",
    "completed_at": "2026-05-12T00:17:51.740866+00:00",
    "duration": 3.12
  },
  "prompt_00173": {
    "status": "done",
    "completed_at": "2026-05-12T00:18:05.657868+00:00",
    "duration": 2.64
  },
  "prompt_00174": {
    "status": "done",
    "completed_at": "2026-05-12T00:18:23.463512+00:00",
    "duration": 3.8
  },
  "prompt_00175": {
    "status": "done",
    "completed_at": "2026-05-12T00:18:39.858798+00:00",
    "duration": 3.12
  },
  "prompt_00176": {
    "status": "done",
    "completed_at": "2026-05-12T00:18:50.798390+00:00",
    "duration": 1.64
  },
  "prompt_00177": {
    "status": "done",
    "completed_at": "2026-05-12T00:19:04.605787+00:00",
    "duration": 2.6
  },
  "prompt_00178": {
    "status": "done",
    "completed_at": "2026-05-12T00:19:18.028855+00:00",
    "duration": 2.48
  },
  "prompt_00179": {
    "status": "done",
    "completed_at": "2026-05-12T00:19:29.652919+00:00",
    "duration": 1.88
  },
  "prompt_00180": {
    "status": "done",
    "completed_at": "2026-05-12T00:19:47.609468+00:00",
    "duration": 3.84
  },
  "prompt_00181": {
    "status": "done",
    "completed_at": "2026-05-12T00:20:01.756191+00:00",
    "duration": 2.68
  },
  "prompt_00182": {
    "status": "done",
    "completed_at": "2026-05-12T00:20:17.489181+00:00",
    "duration": 3.16
  },
  "prompt_00183": {
    "status": "done",
    "completed_at": "2026-05-12T00:20:33.457113+00:00",
    "duration": 3.24
  },
  "prompt_00184": {
    "status": "done",
    "completed_at": "2026-05-12T00:20:47.085667+00:00",
    "duration": 2.52
  },
  "prompt_00185": {
    "status": "done",
    "completed_at": "2026-05-12T00:20:58.834588+00:00",
    "duration": 1.96
  },
  "prompt_00186": {
    "status": "done",
    "completed_at": "2026-05-12T00:21:15.167911+00:00",
    "duration": 3.4
  },
  "prompt_00187": {
    "status": "done",
    "completed_at": "2026-05-12T00:21:32.260440+00:00",
    "duration": 3.64
  },
  "prompt_00188": {
    "status": "done",
    "completed_at": "2026-05-12T00:21:45.409568+00:00",
    "duration": 2.36
  },
  "prompt_00189": {
    "status": "done",
    "completed_at": "2026-05-12T00:21:58.988556+00:00",
    "duration": 2.52
  },
  "prompt_00190": {
    "status": "done",
    "completed_at": "2026-05-12T00:22:12.230883+00:00",
    "duration": 2.48
  },
  "prompt_00191": {
    "status": "done",
    "completed_at": "2026-05-12T00:22:30.320681+00:00",
    "duration": 3.92
  },
  "prompt_00192": {
    "status": "done",
    "completed_at": "2026-05-12T00:22:44.477205+00:00",
    "duration": 2.68
  },
  "prompt_00193": {
    "status": "done",
    "completed_at": "2026-05-12T00:23:00.016046+00:00",
    "duration": 3.16
  },
  "prompt_00194": {
    "status": "done",
    "completed_at": "2026-05-12T00:23:12.352618+00:00",
    "duration": 2.16
  },
  "prompt_00195": {
    "status": "done",
    "completed_at": "2026-05-12T00:23:30.408121+00:00",
    "duration": 3.96
  },
  "prompt_00196": {
    "status": "done",
    "completed_at": "2026-05-12T00:23:44.486426+00:00",
    "duration": 2.6
  },
  "prompt_00197": {
    "status": "done",
    "completed_at": "2026-05-12T00:24:03.412969+00:00",
    "duration": 4.16
  },
  "prompt_00198": {
    "status": "done",
    "completed_at": "2026-05-12T00:24:16.883607+00:00",
    "duration": 2.52
  },
  "prompt_00199": {
    "status": "done",
    "completed_at": "2026-05-12T00:24:33.845359+00:00",
    "duration": 3.64
  },
  "prompt_00200": {
    "status": "done",
    "completed_at": "2026-05-12T00:24:50.713081+00:00",
    "duration": 3.64
  },
  "prompt_00201": {
    "status": "done",
    "completed_at": "2026-05-12T00:25:04.982790+00:00",
    "duration": 2.72
  },
  "prompt_00202": {
    "status": "done",
    "completed_at": "2026-05-12T00:25:20.827918+00:00",
    "duration": 3.2
  },
  "prompt_00203": {
    "status": "done",
    "completed_at": "2026-05-12T00:25:34.208890+00:00",
    "duration": 2.48
  },
  "prompt_00204": {
    "status": "done",
    "completed_at": "2026-05-12T00:25:48.557681+00:00",
    "duration": 2.76
  },
  "prompt_00205": {
    "status": "done",
    "completed_at": "2026-05-12T00:26:00.368682+00:00",
    "duration": 1.96
  },
  "prompt_00206": {
    "status": "done",
    "completed_at": "2026-05-12T00:26:13.732492+00:00",
    "duration": 2.52
  },
  "prompt_00207": {
    "status": "done",
    "completed_at": "2026-05-12T00:26:32.898255+00:00",
    "duration": 4.24
  },
  "prompt_00208": {
    "status": "done",
    "completed_at": "2026-05-12T00:26:47.388080+00:00",
    "duration": 2.68
  },
  "prompt_00209": {
    "status": "done",
    "completed_at": "2026-05-12T00:27:02.766583+00:00",
    "duration": 3.08
  },
  "prompt_00210": {
    "status": "done",
    "completed_at": "2026-05-12T00:27:19.380848+00:00",
    "duration": 3.44
  },
  "prompt_00211": {
    "status": "done",
    "completed_at": "2026-05-12T00:27:36.742042+00:00",
    "duration": 3.68
  },
  "prompt_00212": {
    "status": "done",
    "completed_at": "2026-05-12T00:27:53.204676+00:00",
    "duration": 3.4
  },
  "prompt_00213": {
    "status": "done",
    "completed_at": "2026-05-12T00:28:08.638131+00:00",
    "duration": 3.04
  },
  "prompt_00214": {
    "status": "done",
    "completed_at": "2026-05-12T00:28:25.273662+00:00",
    "duration": 3.4
  },
  "prompt_00215": {
    "status": "done",
    "completed_at": "2026-05-12T00:28:40.136845+00:00",
    "duration": 2.92
  },
  "prompt_00216": {
    "status": "done",
    "completed_at": "2026-05-12T00:28:58.262676+00:00",
    "duration": 3.92
  },
  "prompt_00217": {
    "status": "done",
    "completed_at": "2026-05-12T00:29:12.679704+00:00",
    "duration": 2.76
  },
  "prompt_00218": {
    "status": "done",
    "completed_at": "2026-05-12T00:29:31.447665+00:00",
    "duration": 4.08
  },
  "prompt_00219": {
    "status": "done",
    "completed_at": "2026-05-12T00:29:48.551131+00:00",
    "duration": 3.6
  },
  "prompt_00220": {
    "status": "done",
    "completed_at": "2026-05-12T00:30:06.314955+00:00",
    "duration": 3.76
  },
  "prompt_00221": {
    "status": "done",
    "completed_at": "2026-05-12T00:30:20.197837+00:00",
    "duration": 2.6
  },
  "prompt_00222": {
    "status": "done",
    "completed_at": "2026-05-12T00:30:34.866307+00:00",
    "duration": 2.84
  },
  "prompt_00223": {
    "status": "done",
    "completed_at": "2026-05-12T00:30:52.499780+00:00",
    "duration": 3.72
  },
  "prompt_00224": {
    "status": "done",
    "completed_at": "2026-05-12T00:31:06.784143+00:00",
    "duration": 2.68
  },
  "prompt_00225": {
    "status": "done",
    "completed_at": "2026-05-12T00:31:23.537500+00:00",
    "duration": 3.44
  },
  "prompt_00226": {
    "status": "done",
    "completed_at": "2026-05-12T00:31:37.452120+00:00",
    "duration": 2.6
  },
  "prompt_00227": {
    "status": "done",
    "completed_at": "2026-05-12T00:31:53.001293+00:00",
    "duration": 3.08
  },
  "prompt_00228": {
    "status": "done",
    "completed_at": "2026-05-12T00:32:10.931163+00:00",
    "duration": 3.84
  },
  "prompt_00229": {
    "status": "done",
    "completed_at": "2026-05-12T00:32:27.791780+00:00",
    "duration": 3.48
  },
  "prompt_00230": {
    "status": "done",
    "completed_at": "2026-05-12T00:32:42.435523+00:00",
    "duration": 2.8
  },
  "prompt_00231": {
    "status": "done",
    "completed_at": "2026-05-12T00:32:56.017411+00:00",
    "duration": 2.48
  },
  "prompt_00232": {
    "status": "done",
    "completed_at": "2026-05-12T00:33:12.603623+00:00",
    "duration": 3.4
  },
  "prompt_00233": {
    "status": "done",
    "completed_at": "2026-05-12T00:33:30.460297+00:00",
    "duration": 3.8
  },
  "prompt_00234": {
    "status": "done",
    "completed_at": "2026-05-12T00:33:46.349149+00:00",
    "duration": 3.2
  },
  "prompt_00235": {
    "status": "done",
    "completed_at": "2026-05-12T00:34:01.049901+00:00",
    "duration": 2.84
  },
  "prompt_00236": {
    "status": "done",
    "completed_at": "2026-05-12T00:34:16.983843+00:00",
    "duration": 3.24
  },
  "prompt_00237": {
    "status": "done",
    "completed_at": "2026-05-12T00:34:31.629608+00:00",
    "duration": 2.84
  },
  "prompt_00238": {
    "status": "done",
    "completed_at": "2026-05-12T00:34:44.233680+00:00",
    "duration": 2.16
  },
  "prompt_00239": {
    "status": "done",
    "completed_at": "2026-05-12T00:35:02.515940+00:00",
    "duration": 3.92
  },
  "prompt_00240": {
    "status": "done",
    "completed_at": "2026-05-12T00:35:17.609873+00:00",
    "duration": 2.92
  },
  "prompt_00241": {
    "status": "done",
    "completed_at": "2026-05-12T00:35:32.558333+00:00",
    "duration": 2.96
  },
  "prompt_00242": {
    "status": "done",
    "completed_at": "2026-05-12T00:35:47.241019+00:00",
    "duration": 2.88
  },
  "prompt_00243": {
    "status": "done",
    "completed_at": "2026-05-12T00:35:59.046381+00:00",
    "duration": 1.96
  },
  "prompt_00244": {
    "status": "done",
    "completed_at": "2026-05-12T00:36:14.457267+00:00",
    "duration": 3.12
  },
  "prompt_00245": {
    "status": "done",
    "completed_at": "2026-05-12T00:36:28.933022+00:00",
    "duration": 2.84
  },
  "prompt_00246": {
    "status": "done",
    "completed_at": "2026-05-12T00:36:42.487734+00:00",
    "duration": 2.56
  },
  "prompt_00247": {
    "status": "done",
    "completed_at": "2026-05-12T00:36:56.898132+00:00",
    "duration": 2.8
  },
  "prompt_00248": {
    "status": "done",
    "completed_at": "2026-05-12T00:37:14.964293+00:00",
    "duration": 3.88
  },
  "prompt_00249": {
    "status": "done",
    "completed_at": "2026-05-12T00:37:30.776087+00:00",
    "duration": 3.24
  },
  "prompt_00250": {
    "status": "done",
    "completed_at": "2026-05-12T00:37:45.531168+00:00",
    "duration": 2.92
  },
  "prompt_00251": {
    "status": "done",
    "completed_at": "2026-05-12T00:38:00.319262+00:00",
    "duration": 2.88
  },
  "prompt_00252": {
    "status": "done",
    "completed_at": "2026-05-12T00:38:15.826108+00:00",
    "duration": 3.2
  },
  "prompt_00253": {
    "status": "done",
    "completed_at": "2026-05-12T00:38:31.860239+00:00",
    "duration": 3.32
  },
  "prompt_00254": {
    "status": "done",
    "completed_at": "2026-05-12T00:38:46.022773+00:00",
    "duration": 2.76
  },
  "prompt_00255": {
    "status": "done",
    "completed_at": "2026-05-12T00:39:00.923704+00:00",
    "duration": 2.96
  },
  "prompt_00256": {
    "status": "done",
    "completed_at": "2026-05-12T00:39:18.148273+00:00",
    "duration": 3.72
  },
  "prompt_00257": {
    "status": "done",
    "completed_at": "2026-05-12T00:39:33.318978+00:00",
    "duration": 3.08
  },
  "prompt_00258": {
    "status": "done",
    "completed_at": "2026-05-12T00:39:49.239641+00:00",
    "duration": 3.28
  },
  "prompt_00259": {
    "status": "done",
    "completed_at": "2026-05-12T00:40:02.627821+00:00",
    "duration": 2.44
  },
  "prompt_00260": {
    "status": "done",
    "completed_at": "2026-05-12T00:40:15.993193+00:00",
    "duration": 2.48
  },
  "prompt_00261": {
    "status": "done",
    "completed_at": "2026-05-12T00:40:29.472044+00:00",
    "duration": 2.52
  },
  "prompt_00262": {
    "status": "done",
    "completed_at": "2026-05-12T00:40:41.931903+00:00",
    "duration": 2.2
  },
  "prompt_00263": {
    "status": "done",
    "completed_at": "2026-05-12T00:40:57.334560+00:00",
    "duration": 3.12
  },
  "prompt_00264": {
    "status": "done",
    "completed_at": "2026-05-12T00:41:09.154391+00:00",
    "duration": 1.92
  },
  "prompt_00265": {
    "status": "done",
    "completed_at": "2026-05-12T00:41:22.242184+00:00",
    "duration": 2.4
  },
  "prompt_00266": {
    "status": "done",
    "completed_at": "2026-05-12T00:41:33.259902+00:00",
    "duration": 1.72
  },
  "prompt_00267": {
    "status": "done",
    "completed_at": "2026-05-12T00:41:48.116442+00:00",
    "duration": 2.96
  },
  "prompt_00268": {
    "status": "done",
    "completed_at": "2026-05-12T00:42:02.271670+00:00",
    "duration": 2.68
  },
  "prompt_00269": {
    "status": "done",
    "completed_at": "2026-05-12T00:42:15.559450+00:00",
    "duration": 2.4
  },
  "prompt_00270": {
    "status": "done",
    "completed_at": "2026-05-12T00:42:32.147356+00:00",
    "duration": 3.44
  },
  "prompt_00271": {
    "status": "done",
    "completed_at": "2026-05-12T00:42:43.999665+00:00",
    "duration": 1.96
  },
  "prompt_00272": {
    "status": "done",
    "completed_at": "2026-05-12T00:43:01.157295+00:00",
    "duration": 3.6
  },
  "prompt_00273": {
    "status": "done",
    "completed_at": "2026-05-12T00:43:15.325266+00:00",
    "duration": 2.68
  },
  "prompt_00274": {
    "status": "done",
    "completed_at": "2026-05-12T00:43:32.399864+00:00",
    "duration": 3.56
  },
  "prompt_00275": {
    "status": "done",
    "completed_at": "2026-05-12T00:43:48.580161+00:00",
    "duration": 3.32
  },
  "prompt_00276": {
    "status": "done",
    "completed_at": "2026-05-12T00:44:03.502720+00:00",
    "duration": 2.84
  },
  "prompt_00277": {
    "status": "done",
    "completed_at": "2026-05-12T00:44:18.775193+00:00",
    "duration": 2.76
  },
  "prompt_00278": {
    "status": "done",
    "completed_at": "2026-05-12T00:44:35.260180+00:00",
    "duration": 3.04
  },
  "prompt_00279": {
    "status": "done",
    "completed_at": "2026-05-12T00:44:50.606311+00:00",
    "duration": 2.84
  },
  "prompt_00280": {
    "status": "done",
    "completed_at": "2026-05-12T00:45:05.681181+00:00",
    "duration": 2.76
  },
  "prompt_00281": {
    "status": "done",
    "completed_at": "2026-05-12T00:45:19.843764+00:00",
    "duration": 2.6
  },
  "prompt_00282": {
    "status": "done",
    "completed_at": "2026-05-12T00:45:31.465186+00:00",
    "duration": 1.88
  },
  "prompt_00283": {
    "status": "done",
    "completed_at": "2026-05-12T00:45:45.224028+00:00",
    "duration": 2.56
  },
  "prompt_00284": {
    "status": "done",
    "completed_at": "2026-05-12T00:45:59.890056+00:00",
    "duration": 2.84
  },
  "prompt_00285": {
    "status": "done",
    "completed_at": "2026-05-12T00:46:11.468307+00:00",
    "duration": 1.88
  },
  "prompt_00286": {
    "status": "done",
    "completed_at": "2026-05-12T00:46:26.515566+00:00",
    "duration": 2.96
  },
  "prompt_00287": {
    "status": "done",
    "completed_at": "2026-05-12T00:46:39.402050+00:00",
    "duration": 2.28
  },
  "prompt_00288": {
    "status": "done",
    "completed_at": "2026-05-12T00:46:52.951363+00:00",
    "duration": 2.52
  },
  "prompt_00289": {
    "status": "done",
    "completed_at": "2026-05-12T00:47:06.132769+00:00",
    "duration": 2.36
  },
  "prompt_00290": {
    "status": "done",
    "completed_at": "2026-05-12T00:47:21.667808+00:00",
    "duration": 3.08
  },
  "prompt_00291": {
    "status": "done",
    "completed_at": "2026-05-12T00:47:37.296828+00:00",
    "duration": 2.92
  },
  "prompt_00292": {
    "status": "done",
    "completed_at": "2026-05-12T00:47:49.238234+00:00",
    "duration": 1.92
  },
  "prompt_00293": {
    "status": "done",
    "completed_at": "2026-05-12T00:48:03.693119+00:00",
    "duration": 2.68
  },
  "prompt_00294": {
    "status": "done",
    "completed_at": "2026-05-12T00:48:19.206061+00:00",
    "duration": 2.76
  },
  "prompt_00295": {
    "status": "done",
    "completed_at": "2026-05-12T00:48:33.723197+00:00",
    "duration": 2.44
  },
  "prompt_00296": {
    "status": "done",
    "completed_at": "2026-05-12T00:48:45.680387+00:00",
    "duration": 1.88
  },
  "prompt_00297": {
    "status": "done",
    "completed_at": "2026-05-12T00:49:01.262637+00:00",
    "duration": 2.8
  },
  "prompt_00298": {
    "status": "done",
    "completed_at": "2026-05-12T00:49:15.699604+00:00",
    "duration": 2.64
  },
  "prompt_00299": {
    "status": "done",
    "completed_at": "2026-05-12T00:49:29.532405+00:00",
    "duration": 2.52
  },
  "prompt_00300": {
    "status": "done",
    "completed_at": "2026-05-12T00:49:44.040372+00:00",
    "duration": 2.8
  },
  "prompt_00301": {
    "status": "done",
    "completed_at": "2026-05-12T00:49:54.749821+00:00",
    "duration": 1.56
  },
  "prompt_00302": {
    "status": "done",
    "completed_at": "2026-05-12T00:50:05.231456+00:00",
    "duration": 1.52
  },
  "prompt_00303": {
    "status": "done",
    "completed_at": "2026-05-12T00:50:19.849546+00:00",
    "duration": 2.84
  },
  "prompt_00304": {
    "status": "done",
    "completed_at": "2026-05-12T00:50:31.151258+00:00",
    "duration": 1.8
  },
  "prompt_00305": {
    "status": "done",
    "completed_at": "2026-05-12T00:50:43.016388+00:00",
    "duration": 1.84
  },
  "prompt_00306": {
    "status": "done",
    "completed_at": "2026-05-12T00:50:54.112248+00:00",
    "duration": 1.64
  },
  "prompt_00307": {
    "status": "done",
    "completed_at": "2026-05-12T00:51:05.977258+00:00",
    "duration": 1.68
  },
  "prompt_00308": {
    "status": "done",
    "completed_at": "2026-05-12T00:51:17.607983+00:00",
    "duration": 1.6
  },
  "prompt_00309": {
    "status": "done",
    "completed_at": "2026-05-12T00:51:28.931084+00:00",
    "duration": 1.6
  },
  "prompt_00310": {
    "status": "done",
    "completed_at": "2026-05-12T00:51:40.414845+00:00",
    "duration": 1.64
  },
  "prompt_00311": {
    "status": "done",
    "completed_at": "2026-05-12T00:51:52.746556+00:00",
    "duration": 1.84
  },
  "prompt_00312": {
    "status": "done",
    "completed_at": "2026-05-12T00:52:03.749394+00:00",
    "duration": 1.64
  },
  "prompt_00313": {
    "status": "done",
    "completed_at": "2026-05-12T00:52:16.358372+00:00",
    "duration": 2.08
  },
  "prompt_00314": {
    "status": "done",
    "completed_at": "2026-05-12T00:52:27.505527+00:00",
    "duration": 1.64
  },
  "prompt_00315": {
    "status": "done",
    "completed_at": "2026-05-12T00:52:39.403027+00:00",
    "duration": 1.96
  },
  "prompt_00316": {
    "status": "done",
    "completed_at": "2026-05-12T00:52:48.700938+00:00",
    "duration": 1.08
  },
  "prompt_00317": {
    "status": "done",
    "completed_at": "2026-05-12T00:52:57.718972+00:00",
    "duration": 1.04
  },
  "prompt_00318": {
    "status": "done",
    "completed_at": "2026-05-12T00:53:07.387299+00:00",
    "duration": 1.2
  },
  "prompt_00319": {
    "status": "done",
    "completed_at": "2026-05-12T00:53:17.600082+00:00",
    "duration": 1.36
  },
  "prompt_00320": {
    "status": "done",
    "completed_at": "2026-05-12T00:53:29.464770+00:00",
    "duration": 1.92
  },
  "prompt_00321": {
    "status": "done",
    "completed_at": "2026-05-12T00:53:43.374852+00:00",
    "duration": 2.48
  },
  "prompt_00322": {
    "status": "done",
    "completed_at": "2026-05-12T00:53:54.000926+00:00",
    "duration": 1.4
  },
  "prompt_00323": {
    "status": "done",
    "completed_at": "2026-05-12T00:54:03.567484+00:00",
    "duration": 1.16
  },
  "prompt_00324": {
    "status": "done",
    "completed_at": "2026-05-12T00:54:13.008964+00:00",
    "duration": 1.16
  },
  "prompt_00325": {
    "status": "done",
    "completed_at": "2026-05-12T00:54:21.829076+00:00",
    "duration": 0.96
  },
  "prompt_00326": {
    "status": "done",
    "completed_at": "2026-05-12T00:54:32.034045+00:00",
    "duration": 1.36
  },
  "prompt_00327": {
    "status": "done",
    "completed_at": "2026-05-12T00:54:44.387826+00:00",
    "duration": 2.0
  },
  "prompt_00328": {
    "status": "done",
    "completed_at": "2026-05-12T00:54:56.730129+00:00",
    "duration": 1.84
  },
  "prompt_00329": {
    "status": "done",
    "completed_at": "2026-05-12T00:55:06.472177+00:00",
    "duration": 0.96
  },
  "prompt_00330": {
    "status": "done",
    "completed_at": "2026-05-12T00:55:18.651755+00:00",
    "duration": 1.84
  },
  "prompt_00331": {
    "status": "done",
    "completed_at": "2026-05-12T00:55:28.292824+00:00",
    "duration": 1.12
  },
  "prompt_00332": {
    "status": "done",
    "completed_at": "2026-05-12T00:55:40.309910+00:00",
    "duration": 1.8
  },
  "prompt_00333": {
    "status": "done",
    "completed_at": "2026-05-12T00:55:50.942583+00:00",
    "duration": 1.44
  },
  "prompt_00334": {
    "status": "done",
    "completed_at": "2026-05-12T00:56:04.006572+00:00",
    "duration": 2.16
  },
  "prompt_00335": {
    "status": "done",
    "completed_at": "2026-05-12T00:56:14.083812+00:00",
    "duration": 1.28
  },
  "prompt_00336": {
    "status": "done",
    "completed_at": "2026-05-12T00:56:24.924367+00:00",
    "duration": 1.56
  },
  "prompt_00337": {
    "status": "done",
    "completed_at": "2026-05-12T00:56:33.758532+00:00",
    "duration": 0.88
  },
  "prompt_00338": {
    "status": "done",
    "completed_at": "2026-05-12T00:56:43.072924+00:00",
    "duration": 1.0
  },
  "prompt_00339": {
    "status": "done",
    "completed_at": "2026-05-12T00:56:53.156560+00:00",
    "duration": 1.32
  }
}